targen/__init__.py
targen/data/__init__.py
targen/data/target.py
targen-0.2.1.dist-info/METADATA
targen-0.2.1.dist-info/WHEEL
targen-0.2.1.dist-info/top_level.txt
targen-0.2.1.dist-info/RECORD
